qiskit_nature_pyscf/VERSION.txt
qiskit_nature_pyscf/__init__.py
qiskit_nature_pyscf/py.typed
qiskit_nature_pyscf/pyscf_ground_state_solver.py
qiskit_nature_pyscf/qiskit_solver.py
qiskit_nature_pyscf/version.py
qiskit_nature_pyscf-0.4.0.dist-info/LICENSE.txt
qiskit_nature_pyscf-0.4.0.dist-info/METADATA
qiskit_nature_pyscf-0.4.0.dist-info/WHEEL
qiskit_nature_pyscf-0.4.0.dist-info/top_level.txt
qiskit_nature_pyscf-0.4.0.dist-info/RECORD
