Metadata-Version: 2.1
Name: qiskit-nature-pyscf
Version: 0.4.0
Summary: Qiskit Nature PySCF: Third-party integration plugin of Qiskit Nature + PySCF.
Home-page: https://github.com/qiskit-community/qiskit-nature-pyscf
Author: Qiskit Nature PySCF Development Team
Author-email: qiskit@us.ibm.com
License: Apache-2.0
Project-URL: Bug Tracker, https://github.com/qiskit-community/qiskit-nature-pyscf/issues
Project-URL: Documentation, https://qiskit-community.github.io/qiskit-nature-pyscf/
Project-URL: Source Code, https://github.com/qiskit-community/qiskit-nature-pyscf
Keywords: qiskit sdk quantum nature chemistry physics pyscf
Classifier: Environment :: Console
Classifier: License :: OSI Approved :: Apache Software License
Classifier: Intended Audience :: Developers
Classifier: Intended Audience :: Science/Research
Classifier: Operating System :: MacOS
Classifier: Operating System :: POSIX :: Linux
Classifier: Programming Language :: Python :: 3 :: Only
Classifier: Programming Language :: Python :: 3.8
Classifier: Programming Language :: Python :: 3.9
Classifier: Programming Language :: Python :: 3.10
Classifier: Programming Language :: Python :: 3.11
Classifier: Programming Language :: Python :: 3.12
Classifier: Topic :: Scientific/Engineering
Requires-Python: >=3.8
License-File: LICENSE.txt
Requires-Dist: qiskit-nature >=0.7.1
Requires-Dist: pyscf >=2.0
